pyexecutable_gen.py
pyexecutable_gen-0.0.3.dist-info/licenses/LICENSE
pyexecutable_gen-0.0.3.dist-info/METADATA
pyexecutable_gen-0.0.3.dist-info/WHEEL
pyexecutable_gen-0.0.3.dist-info/top_level.txt
pyexecutable_gen-0.0.3.dist-info/RECORD
