Metadata-Version: 2.4
Name: pyexecutable_gen
Version: 0.0.3
Summary: A Python wrapper for PyInstaller to programmatically generate an executable from a Python script
Author-email: keralaboy <keralaboypypi@keralaboy.anonaddy.com>
License-Expression: MIT
Project-URL: Homepage, https://github.com/its-me-abi/pyexecutable_gen
Keywords: pyinstaller,exe,executable,generate
Classifier: Development Status :: 4 - Beta
Classifier: Programming Language :: Python
Requires-Python: >=3.6
License-File: LICENSE
Requires-Dist: pyinstaller
Dynamic: license-file
